scrapis
