Metadata-Version: 2.1
Name: scrapis
Version: 1.0.5
Summary: Google Apps Scrapper
Home-page: https://github.com/redzoua/scrapis
Author: Redzoua
Author-email: Redzoua <mthaqafiah@gmail.com>
License: Copyright (c) 2018 The Python Packaging Authority
Project-URL: Homepage, https://github.com/pypa/sampleproject
Project-URL: Bug Tracker, https://github.com/pypa/sampleproject/issues
Classifier: Programming Language :: Python :: 3
Classifier: License :: OSI Approved :: MIT License
Classifier: Operating System :: OS Independent
Requires-Python: >=3.7
License-File: LICENSE
